pagevalidation/__init__.py
pagevalidation/pageval.py
cpphospitalproject-0.1.0.dist-info/METADATA
cpphospitalproject-0.1.0.dist-info/WHEEL
cpphospitalproject-0.1.0.dist-info/top_level.txt
cpphospitalproject-0.1.0.dist-info/RECORD
